efsm/__init__.py
efsm/micro/__init__.py
efsm/micro/core.py
efsm/shell/__init__.py
efsm/shell/core.py
efsm/standard/__init__.py
efsm/standard/core.py
efsm-0.2.5.2.dist-info/METADATA
efsm-0.2.5.2.dist-info/WHEEL
efsm-0.2.5.2.dist-info/top_level.txt
efsm-0.2.5.2.dist-info/RECORD
